agoraiot/__init__.py
agoraiot/version.py
agoraiot-3.0.2.dist-info/licenses/LICENSE
agoraiot-3.0.2.dist-info/WHEEL
agoraiot-3.0.2.dist-info/METADATA
agoraiot-3.0.2.dist-info/RECORD
