Metadata-Version: 2.4
Name: agoraiot
Version: 3.0.2
Summary: AgoraIoT Python Libraries
Author-email: AgoraIoT <agoraiot@slb.com>
Classifier: License :: OSI Approved :: Apache Software License
License-File: LICENSE
Requires-Dist: agora_logging == 3.0.2
Requires-Dist: agora_busclient == 3.0.2
Requires-Dist: agora_config == 3.0.2
Requires-Dist: agora_redis_client == 3.0.2
Requires-Dist: agora_twin_property == 3.0.2
Requires-Dist: agora_gps == 3.0.2
Requires-Dist: agora_utils == 3.0.2
Project-URL: Documentation, https://agoraiot.github.io
Project-URL: Home, https://www.agoraiot.com
